LICENSE
MANIFEST.in
README.rst
next_review.py
setup.py
next_review.egg-info/PKG-INFO
next_review.egg-info/SOURCES.txt
next_review.egg-info/dependency_links.txt
next_review.egg-info/entry_points.txt
next_review.egg-info/requires.txt
next_review.egg-info/top_level.txt