Metadata-Version: 1.1
Name: next-review
Version: 1.5.0
Summary: Start your next gerrit code review without any hassle.
Home-page: http://github.com/dolph/next-review
Author: Dolph Mathews
Author-email: dolph.mathews@gmail.com
License: UNKNOWN
Platform: UNKNOWN
Classifier: Development Status :: 5 - Production/Stable
Classifier: Environment :: Console
Classifier: Intended Audience :: Developers
Classifier: Topic :: Utilities
